woofcord/__init__.py
woofcord/channel.py
woofcord/color.py
woofcord/embed.py
woofcord/guild.py
woofcord/intents.py
woofcord/message.py
woofcord/msg.py
woofcord/user.py
WoofCord-1.0.1.dist-info/METADATA
WoofCord-1.0.1.dist-info/WHEEL
WoofCord-1.0.1.dist-info/top_level.txt
WoofCord-1.0.1.dist-info/RECORD
