Metadata-Version: 2.1
Name: WoofCord
Version: 1.0.1
Summary: WoofCord is a easier and faster version of discord.py
Author: Lordpomind
Author-email: lordpomind@gmail.com
Classifier: Programming Language :: Python :: 3
Classifier: License :: OSI Approved :: MIT License
Classifier: Operating System :: OS Independent
Requires-Python: >=3.6
Requires-Dist: aiohttp
Requires-Dist: websockets
